xh_utils/__init__.py
xh_utils/logger.py
xh_utils-1.2.0.dist-info/LICENSE
xh_utils-1.2.0.dist-info/METADATA
xh_utils-1.2.0.dist-info/WHEEL
xh_utils-1.2.0.dist-info/top_level.txt
xh_utils-1.2.0.dist-info/RECORD
