Metadata-Version: 2.1
Name: xh-utils
Version: 1.2.0
Summary: xh personal Python util libs
Home-page: https://github.com/wfs420100/XhUtils
Author: wfs420100
Author-email: wfs420100@126.com
License: Apache License 2.0
Classifier: Programming Language :: Python :: 3.6
Classifier: Programming Language :: Python :: 3.7
Classifier: Programming Language :: Python :: 3.8
Classifier: Programming Language :: Python :: 3.9
Classifier: Programming Language :: Python :: 3.10
License-File: LICENSE
